hstk/__init__.py
hstk/hscli.py
hstk/hsscript.py
hstk-4.6.6.1.dist-info/LICENSE
hstk-4.6.6.1.dist-info/METADATA
hstk-4.6.6.1.dist-info/WHEEL
hstk-4.6.6.1.dist-info/entry_points.txt
hstk-4.6.6.1.dist-info/top_level.txt
hstk-4.6.6.1.dist-info/RECORD
